verilog/memory/latch/Dflipflop/src/Dflipflop.v
module Dflipflop(preset, data, clk, clear, Q, QN);
   input clear, data, clk, preset;
   output Q, QN;

   wire [5:0] line;

   assign line[0] = ~(clear   | line[3] | line[1]);
   assign line[1] = ~(line[0] | clk     | preset  );
   assign line[2] = ~(line[1] | clk     | line[3]);
   assign line[3] = ~(line[2] | data    | preset  );

   assign line[4] = ~(clear   | line[1] | line[5]);
   assign line[5] = ~(line[4] | line[2] | preset  );

   assign Q = line[4];
   assign QN = line[5];
endmodule

verilog/memory/latch/Dflipflop/test/test_Dflipflop.v
module test_Dflipflop;
   reg a, clk, reset, set;
   wire s1, s2;

   Dflipflop test_Dflipflop(set, a, clk, reset, s1, s2);

   initial
     begin
	$dumpfile("signal_Dflipflop.vcd");
	$dumpvars;
	$display("\t\ttime, \ta, \tset, \treset, \tclk, \ts1, \ts2");
	$monitor("%d \t%b \t%b \t%b \t%b \t%b \t%b", $time, a, set, reset, clk, s1, s2);

	set = 0;
	a = 0;
	clk = 0;
	reset = 1;
	#10;
	a = 0;
	clk = 0;
	reset = 0;
	#10;
	a = 1;
	clk = 1;
	reset = 0;
	#10;
	a = 1;
	clk = 0;
	reset = 0;
	#10;
	a = 0;
	clk = 1;
	reset = 0;
	#10;
	a = 1;
	clk = 0;
	reset = 0;
	#10;
	a = 1;
	clk = 1;
	reset = 0;
	#10;
	a = 1;
	clk = 0;
	reset = 0;
	#10;
	a = 1;
	clk = 0;
	reset = 0;
	#10;
	a = 0;
	clk = 1;
	reset = 1;
	#10;
     end // initial begin

endmodule // test_Dflipflop

verilog/memory/latch/Dflipflop/signal_Dflipflop.vcd
$date
	Thu Jul 13 07:21:13 2023
$end
$version
	Icarus Verilog
$end
$timescale
	1s
$end
$scope module test_Dflipflop $end
$var wire 1 ! s2 $end
$var wire 1 " s1 $end
$var reg 1 # a $end
$var reg 1 $ clk $end
$var reg 1 % reset $end
$var reg 1 & set $end
$scope module test_Dflipflop $end
$var wire 1 % clear $end
$var wire 1 $ clk $end
$var wire 1 # data $end
$var wire 1 & preset $end
$var wire 6 ' line [5:0] $end
$var wire 1 ! QN $end
$var wire 1 " Q $end
$upscope $end
$upscope $end
$enddefinitions $end
#0
$dumpvars
b101010 '
0&
1%
0$
0#
0"
1!
$end
#10
0%
#20
b100001 '
1$
1#
#30
1"
0!
b10101 '
0$
#40
b11000 '
1$
0#
#50
1!
0"
b100010 '
0$
1#
#60
b100001 '
1$
#70
1"
0!
b10101 '
0$
#90
1!
0"
b101000 '
1%
1$
0#
