memory/src/basculeD.v
module basculeD (a, clk, s1, s2);
   input a, clk;
   wire [4:0] line;
   output s1, s2;
   
   gate_nand nand1(a, clk, line[0]);

   gate_not not1(a, line[1]);
   gate_nand nand2(line[1], clk, line[2]);

   gate_nand nand3(line[0], line[4], line[3]);
   gate_nand nand4(line[2], line[3], line[4]);

//   buf buf1(line[3], s1);
//   buf buf2(line[4], s2);
   
   assign s1 = line[3];
   assign s2 = line[4];
endmodule // basculeD
/*
module flip_flopD(a, clk, s);
   input a, clk;
   output s1, s2;
   wire [6:0] line;

   basculeD basc1(a, clk, line[0], line[1]);
   not not1(clk, line[2]);

   nand nand1(line[2], line[0], line[3]);
   nand nand2(line[2], line[1], line[4]);

   nand nand3(line[3], line[5], s1);
   nand nand4(line[4], line[6], s2);
endmodule // flip_flopD
*/

memory/test/test_basculeD.v
module test_basculeD;
   reg a, clk;
   wire s1, s2;

   basculeD test_basculeD(a, clk, s1, s2);

   initial
     begin
	a = 0;
	clk = 0;
	#5;
	a = 1;
	clk = 0;
	#5;
	a = 0;
	clk = 1;
	#5;
	a = 1;
	clk = 1;
	#5;
	a = 0;
	clk = 0;
	#5;
	a = 1;
	clk = 0;
	#5;
	a = 0;
	clk = 1;
	#5;
	a = 1;
	clk = 1;
     end // initial begin
   initial
     begin
	$dumpfile("signal/signal_basculeD.vcd");
	$dumpvars;
     end
   initial
     begin
	$display("\t\ttime, \ta, \tclk, \ts1, \ts2");
	$monitor("%d \t%b \t%b \t%b \t%b", $time, a, clk, s1, s2);
     end
endmodule // test_basculeD

primitive/gate.v
module gate_not (e1, s);
   input e1;
   output s;

   assign s = ~e1;
endmodule // not

module gate_and (e1, e2, s);
   input e1;
   input e2;
   output s;

   assign s = e1 & e2;
endmodule // and

module gate_or (e1, e2, s);
   input e1, e2;
   output s;

   assign s = e1 | e2;
endmodule // or

module gate_xor (e1, e2, s);
   input e1, e2;
   output s;
 
   assign s = e1 ^ e2;
endmodule // xor

module gate_nand (e1, e2, s);
   input e1, e2;
   output s;

   assign s = e1 ~& e2;
endmodule // nand
  
module gate_nor (e1, e2, s);
   input e1, e2;
   output s;

   assign s = e1 ~| e2;
endmodule // nor

memory/signal/signal_basculeD.vcd
$date
	Sat May 23 17:30:51 2020
$end
$version
	Icarus Verilog
$end
$timescale
	1s
$end
$scope module gate_and $end
$var wire 1 ! e1 $end
$var wire 1 " e2 $end
$var wire 1 # s $end
$upscope $end
$scope module gate_nor $end
$var wire 1 $ e1 $end
$var wire 1 % e2 $end
$var wire 1 & s $end
$upscope $end
$scope module gate_or $end
$var wire 1 ' e1 $end
$var wire 1 ( e2 $end
$var wire 1 ) s $end
$upscope $end
$scope module gate_xor $end
$var wire 1 * e1 $end
$var wire 1 + e2 $end
$var wire 1 , s $end
$upscope $end
$scope module test_basculeD $end
$var wire 1 - s2 $end
$var wire 1 . s1 $end
$var reg 1 / a $end
$var reg 1 0 clk $end
$scope module test_basculeD $end
$var wire 1 / a $end
$var wire 1 0 clk $end
$var wire 1 - s2 $end
$var wire 1 . s1 $end
$var wire 5 1 line [4:0] $end
$scope module nand1 $end
$var wire 1 / e1 $end
$var wire 1 0 e2 $end
$var wire 1 2 s $end
$upscope $end
$scope module nand2 $end
$var wire 1 3 e1 $end
$var wire 1 0 e2 $end
$var wire 1 4 s $end
$upscope $end
$scope module nand3 $end
$var wire 1 5 e1 $end
$var wire 1 6 e2 $end
$var wire 1 7 s $end
$upscope $end
$scope module nand4 $end
$var wire 1 8 e1 $end
$var wire 1 9 e2 $end
$var wire 1 : s $end
$upscope $end
$scope module not1 $end
$var wire 1 / e1 $end
$var wire 1 ; s $end
$upscope $end
$upscope $end
$upscope $end
$enddefinitions $end
#0
$dumpvars
1;
x:
x9
18
x7
x6
15
14
13
12
bx111 1
00
0/
x.
x-
x,
z+
z*
x)
z(
z'
x&
z%
z$
x#
z"
z!
$end
#5
03
bx101 1
0;
1/
#10
0.
09
07
1-
16
1:
08
04
13
b10011 1
1;
10
0/
#15
0-
06
0:
1.
19
18
17
14
05
03
02
b1100 1
0;
1/
#20
15
13
12
b1111 1
1;
00
0/
#25
03
b1101 1
0;
1/
#30
0.
09
07
1-
16
1:
08
04
13
b10011 1
1;
10
0/
#35
0-
06
0:
1.
19
18
17
14
05
03
02
b1100 1
0;
1/
