primitive/gate.v
module gate_not (e1, s);
   input e1;
   output s;

   assign s = ~e1;
endmodule // not

module gate_and (e1, e2, s);
   input e1;
   input e2;
   output s;

   assign s = e1 & e2;
endmodule // and

module gate_or (e1, e2, s);
   input e1, e2;
   output s;

   assign s = e1 | e2;
endmodule // or

module gate_xor (e1, e2, s);
   input e1, e2;
   output s;
 
   assign s = e1 ^ e2;
endmodule // xor

module gate_nand (e1, e2, s);
   input e1, e2;
   output s;

   assign s = e1 ~& e2;
endmodule // nand
  
module gate_nor (e1, e2, s);
   input e1, e2;
   output s;

   assign s = e1 ~| e2;
endmodule // nor

memory/test/test_basculeD.v
module test_basculeD;
   reg a, clk, reset;
   wire s1, s2;

   basculeD test_basculeD(a, clk, reset, s1, s2);

   initial
     begin
	a = 0;
	clk = 0;
	reset = 1;
	#5;
	a = 0;
	clk = 0;
	reset = 0;
	#5;
	a = 1;
	clk = 0;
	reset = 0;
	#5;
	a = 0;
	clk = 1;
	reset = 0;
	#5;
	a = 1;
	clk = 1;
	reset = 0;
	#5;
	a = 0;
	clk = 0;
	reset = 0;
	#5;
	a = 1;
	clk = 0;
	reset = 0;
	#5;
	a = 0;
	clk = 1;
	reset = 0;
	#5;
	a = 0;
	clk = 0;
	reset = 0;
	#5;
	a = 0;
	clk = 0;
	reset = 1;
	#5;
     end // initial begin
   initial
     begin
	$dumpfile("signal/signal_basculeD.vcd");
	$dumpvars;
     end
   initial
     begin
	$display("\t\ttime, \ta, \tclk, \treset, \ts1, \ts2");
	$monitor("%d \t%b \t%b \t%b \t%b \t%b", $time, a, clk, reset, s1, s2);
     end
endmodule // test_basculeD

memory/src/basculeD.v
module basculeD (a, clk, reset, s1, s2);
   input a, clk, reset;
   wire [7:0] line;
   output s1, s2;

   gate_xor xor1(a, reset, line[5]);
   gate_and and1(a, line[5], line[6]);

   gate_nand nand1(a, clk, line[0]);
   gate_not not1(line[6], line[1]);
   gate_nand nand2(line[1], clk, line[2]);

   gate_nand nand3(line[0], line[7], line[3]);
   gate_nand nand4(line[2], line[3], line[4]);

   gate_or or1(reset, line[4], line[7]);
   
   buf buf1(s1, line[3]);
   buf buf2(s2, line[4]);
endmodule // basculeD

module Dflip_flop(a, clk, reset, s1, s2);
   input a, clk, reset;
   output s1, s2;
   wire [3:0] line;
   wire       ignore;
   
   basculeD basc1(a, clk, reset, line[0], ignore);
   gate_not not1(clk, line[1]);
   basculeD basc2(line[0], line[1], reset, line[2], line[3]);

   buf buf1(s1, line[2]);
   buf buf1(s2, line[3]);   
endmodule // flip_flopD

memory/signal/signal_basculeD.vcd
$date
	Sun May 24 00:06:37 2020
$end
$version
	Icarus Verilog
$end
$timescale
	1s
$end
$scope module Dflip_flop $end
$var wire 1 ! a $end
$var wire 1 " clk $end
$var wire 1 # reset $end
$var wire 1 $ s1 $end
$var wire 1 % s2 $end
$var wire 4 & line [3:0] $end
$var wire 1 ' ignore $end
$scope module basc1 $end
$var wire 1 ! a $end
$var wire 1 " clk $end
$var wire 1 # reset $end
$var wire 1 ( s1 $end
$var wire 1 ' s2 $end
$var wire 8 ) line [7:0] $end
$scope module and1 $end
$var wire 1 ! e1 $end
$var wire 1 * e2 $end
$var wire 1 + s $end
$upscope $end
$scope module nand1 $end
$var wire 1 ! e1 $end
$var wire 1 " e2 $end
$var wire 1 , s $end
$upscope $end
$scope module nand2 $end
$var wire 1 - e1 $end
$var wire 1 " e2 $end
$var wire 1 . s $end
$upscope $end
$scope module nand3 $end
$var wire 1 / e1 $end
$var wire 1 0 e2 $end
$var wire 1 1 s $end
$upscope $end
$scope module nand4 $end
$var wire 1 2 e1 $end
$var wire 1 3 e2 $end
$var wire 1 4 s $end
$upscope $end
$scope module not1 $end
$var wire 1 5 e1 $end
$var wire 1 6 s $end
$upscope $end
$scope module or1 $end
$var wire 1 # e1 $end
$var wire 1 7 e2 $end
$var wire 1 8 s $end
$upscope $end
$scope module xor1 $end
$var wire 1 ! e1 $end
$var wire 1 # e2 $end
$var wire 1 9 s $end
$upscope $end
$upscope $end
$scope module basc2 $end
$var wire 1 : a $end
$var wire 1 ; clk $end
$var wire 1 # reset $end
$var wire 1 < s1 $end
$var wire 1 = s2 $end
$var wire 8 > line [7:0] $end
$scope module and1 $end
$var wire 1 : e1 $end
$var wire 1 ? e2 $end
$var wire 1 @ s $end
$upscope $end
$scope module nand1 $end
$var wire 1 : e1 $end
$var wire 1 ; e2 $end
$var wire 1 A s $end
$upscope $end
$scope module nand2 $end
$var wire 1 B e1 $end
$var wire 1 ; e2 $end
$var wire 1 C s $end
$upscope $end
$scope module nand3 $end
$var wire 1 D e1 $end
$var wire 1 E e2 $end
$var wire 1 F s $end
$upscope $end
$scope module nand4 $end
$var wire 1 G e1 $end
$var wire 1 H e2 $end
$var wire 1 I s $end
$upscope $end
$scope module not1 $end
$var wire 1 J e1 $end
$var wire 1 K s $end
$upscope $end
$scope module or1 $end
$var wire 1 # e1 $end
$var wire 1 L e2 $end
$var wire 1 M s $end
$upscope $end
$scope module xor1 $end
$var wire 1 : e1 $end
$var wire 1 # e2 $end
$var wire 1 N s $end
$upscope $end
$upscope $end
$scope module not1 $end
$var wire 1 " e1 $end
$var wire 1 O s $end
$upscope $end
$upscope $end
$scope module gate_nor $end
$var wire 1 P e1 $end
$var wire 1 Q e2 $end
$var wire 1 R s $end
$upscope $end
$scope module test_basculeD $end
$var wire 1 S s2 $end
$var wire 1 T s1 $end
$var reg 1 U a $end
$var reg 1 V clk $end
$var reg 1 W reset $end
$scope module test_basculeD $end
$var wire 1 U a $end
$var wire 1 V clk $end
$var wire 1 W reset $end
$var wire 1 T s1 $end
$var wire 1 S s2 $end
$var wire 8 X line [7:0] $end
$scope module and1 $end
$var wire 1 U e1 $end
$var wire 1 Y e2 $end
$var wire 1 Z s $end
$upscope $end
$scope module nand1 $end
$var wire 1 U e1 $end
$var wire 1 V e2 $end
$var wire 1 [ s $end
$upscope $end
$scope module nand2 $end
$var wire 1 \ e1 $end
$var wire 1 V e2 $end
$var wire 1 ] s $end
$upscope $end
$scope module nand3 $end
$var wire 1 ^ e1 $end
$var wire 1 _ e2 $end
$var wire 1 ` s $end
$upscope $end
$scope module nand4 $end
$var wire 1 a e1 $end
$var wire 1 b e2 $end
$var wire 1 c s $end
$upscope $end
$scope module not1 $end
$var wire 1 d e1 $end
$var wire 1 e s $end
$upscope $end
$scope module or1 $end
$var wire 1 W e1 $end
$var wire 1 f e2 $end
$var wire 1 g s $end
$upscope $end
$scope module xor1 $end
$var wire 1 U e1 $end
$var wire 1 W e2 $end
$var wire 1 h s $end
$upscope $end
$upscope $end
$upscope $end
$enddefinitions $end
#0
$dumpvars
1h
1g
1f
1e
0d
1c
0b
1a
0`
1_
1^
1]
1\
1[
0Z
1Y
b10110111 X
1W
0V
0U
0T
1S
xR
zQ
zP
zO
xN
xM
xL
xK
xJ
xI
xH
xG
xF
xE
xD
xC
xB
xA
x@
x?
bx >
x=
x<
z;
x:
x9
x8
x7
x6
x5
x4
x3
x2
x1
x0
x/
x.
x-
x,
x+
x*
bx )
x(
x'
bxzx &
x%
x$
z#
z"
z!
$end
#5
0Y
b10010111 X
0h
0W
#10
0\
0e
1d
1Z
1Y
b11110101 X
1h
1U
#15
0a
0]
1\
1e
0d
0Y
0Z
b10010011 X
0h
1V
0U
#20
0_
0S
0g
0f
0c
1a
1]
0\
1T
0e
1b
1d
1`
1Z
0^
1Y
0[
b1101100 X
1h
1U
#25
1\
1e
0d
1^
0Y
0Z
1[
b1111 X
0h
0V
0U
#30
0\
0e
1d
1Z
1Y
b1101101 X
1h
1U
#35
0T
0b
0`
1_
1S
1g
1f
1c
0a
0]
1\
1e
0d
0Y
0Z
b10010011 X
0h
1V
0U
#40
1a
b10010111 X
1]
0V
#45
1Y
b10110111 X
1h
1W
