memory/src/basculeD.v
module basculeD (a, clk, s1, s2);
   input a, clk;
   wire [4:0] line;
   output s1, s2;
   
   gate_nand nand1(a, clk, line[0]);

   gate_not not1(a, line[1]);
   gate_nand nand2(line[1], clk, line[2]);

   gate_nand nand3(line[0], line[4], line[3]);
   gate_nand nand4(line[2], line[3], line[4]);

   buf buf1(s1, line[3]);
   buf buf2(s2, line[4]);
endmodule // basculeD

module Dflip_flop(a, clk, s1, s2);
   input a, clk;
   output s1, s2;
   wire [6:0] line;

   basculeD basc1(a, clk, line[0], line[1]);
   gate_not not1(clk, line[2]);

   gate_nand nand1(line[2], line[0], line[3]);
   gate_nand nand2(line[2], line[1], line[4]);

   gate_nand nand3(line[3], line[5], line[6]);
   gate_nand nand4(line[4], line[6], line[5]);

   buf buf1(s1, line[6]);
   buf buf1(s2, line[5]);   
endmodule // flip_flopD

memory/test/test_Dflipflop.v
module test_Dflipflop;
   reg a, clk;
   wire s1, s2;

   Dflip_flop test_Dflipflop(a, clk, s1, s2);

   initial
     begin
	a = 0;
	clk = 0;
	#5;
	a = 1;
	clk = 1;
	#5;
	a = 0;
	clk = 0;
	#5;
	a = 0;
	clk = 1;
	#5;
	a = 0;
	clk = 0;
	#5;
	a = 1;
	clk = 0;
	#5;
	a = 0;
	clk = 1;
	#5;
	a = 1;
	clk = 1;
     end // initial begin
   initial
     begin
	$dumpfile("signal/signal_Dflipflop.vcd");
	$dumpvars;
     end
   initial
     begin
	$display("\t\ttime, \ta, \tclk, \ts1, \ts2");
	$monitor("%d \t%b \t%b \t%b \t%b", $time, a, clk, s1, s2);
     end
endmodule // test_Dflipflop

primitive/gate.v
module gate_not (e1, s);
   input e1;
   output s;

   assign s = ~e1;
endmodule // not

module gate_and (e1, e2, s);
   input e1;
   input e2;
   output s;

   assign s = e1 & e2;
endmodule // and

module gate_or (e1, e2, s);
   input e1, e2;
   output s;

   assign s = e1 | e2;
endmodule // or

module gate_xor (e1, e2, s);
   input e1, e2;
   output s;
 
   assign s = e1 ^ e2;
endmodule // xor

module gate_nand (e1, e2, s);
   input e1, e2;
   output s;

   assign s = e1 ~& e2;
endmodule // nand
  
module gate_nor (e1, e2, s);
   input e1, e2;
   output s;

   assign s = e1 ~| e2;
endmodule // nor

memory/signal/signal_Dflipflop.vcd
$date
	Sat May 23 17:59:16 2020
$end
$version
	Icarus Verilog
$end
$timescale
	1s
$end
$scope module gate_and $end
$var wire 1 ! e1 $end
$var wire 1 " e2 $end
$var wire 1 # s $end
$upscope $end
$scope module gate_nor $end
$var wire 1 $ e1 $end
$var wire 1 % e2 $end
$var wire 1 & s $end
$upscope $end
$scope module gate_or $end
$var wire 1 ' e1 $end
$var wire 1 ( e2 $end
$var wire 1 ) s $end
$upscope $end
$scope module gate_xor $end
$var wire 1 * e1 $end
$var wire 1 + e2 $end
$var wire 1 , s $end
$upscope $end
$scope module test_Dflipflop $end
$var wire 1 - s2 $end
$var wire 1 . s1 $end
$var reg 1 / a $end
$var reg 1 0 clk $end
$scope module test_Dflipflop $end
$var wire 1 / a $end
$var wire 1 0 clk $end
$var wire 1 . s1 $end
$var wire 1 - s2 $end
$var wire 7 1 line [6:0] $end
$scope module basc1 $end
$var wire 1 / a $end
$var wire 1 0 clk $end
$var wire 1 2 s1 $end
$var wire 1 3 s2 $end
$var wire 5 4 line [4:0] $end
$scope module nand1 $end
$var wire 1 / e1 $end
$var wire 1 0 e2 $end
$var wire 1 5 s $end
$upscope $end
$scope module nand2 $end
$var wire 1 6 e1 $end
$var wire 1 0 e2 $end
$var wire 1 7 s $end
$upscope $end
$scope module nand3 $end
$var wire 1 8 e1 $end
$var wire 1 9 e2 $end
$var wire 1 : s $end
$upscope $end
$scope module nand4 $end
$var wire 1 ; e1 $end
$var wire 1 < e2 $end
$var wire 1 = s $end
$upscope $end
$scope module not1 $end
$var wire 1 / e1 $end
$var wire 1 > s $end
$upscope $end
$upscope $end
$scope module nand1 $end
$var wire 1 ? e1 $end
$var wire 1 @ e2 $end
$var wire 1 A s $end
$upscope $end
$scope module nand2 $end
$var wire 1 B e1 $end
$var wire 1 C e2 $end
$var wire 1 D s $end
$upscope $end
$scope module nand3 $end
$var wire 1 E e1 $end
$var wire 1 F e2 $end
$var wire 1 G s $end
$upscope $end
$scope module nand4 $end
$var wire 1 H e1 $end
$var wire 1 I e2 $end
$var wire 1 J s $end
$upscope $end
$scope module not1 $end
$var wire 1 0 e1 $end
$var wire 1 K s $end
$upscope $end
$upscope $end
$upscope $end
$enddefinitions $end
#0
$dumpvars
1K
xJ
xI
xH
xG
xF
xE
xD
xC
1B
xA
x@
1?
1>
x=
x<
1;
x:
x9
18
17
16
15
bx111 4
x3
x2
bx1xx 1
00
0/
x.
x-
x,
z+
z*
x)
z(
z'
x&
z%
z$
x#
z"
z!
$end
#5
0C
1@
03
12
09
1H
1E
1<
0=
1D
1A
1:
1;
0B
0?
08
06
17
bx11001 1
0K
05
b1100 4
0>
10
1/
#10
0-
0F
1.
0J
1I
1G
0E
0A
1B
1?
18
16
b1010101 1
1K
15
b1111 4
1>
00
0/
#15
0@
02
1C
0<
13
0:
19
1E
1=
1A
0;
0B
0?
b10011 4
07
b1011010 1
0K
10
#20
0.
0I
1-
0G
1F
1J
0H
0D
1;
1B
1?
b10111 4
17
b101110 1
1K
00
#25
06
b10101 4
0>
1/
#30
1H
0;
1D
07
0B
0?
16
b111010 1
0K
b10011 4
1>
10
0/
#35
0C
03
1@
09
b111001 1
12
0=
1<
1;
1:
17
08
06
05
b1100 4
0>
1/
