memory/src/basculeD.v
module basculeD (a, clk, reset, s1, s2);
   input a, clk, reset;
   wire [7:0] line;
   output s1, s2;

   gate_xor xor1(a, reset, line[5]);
   gate_and and1(a, line[5], line[6]);

   gate_nand nand1(a, clk, line[0]);
   gate_not not1(line[6], line[1]);
   gate_nand nand2(line[1], clk, line[2]);

   gate_nand nand3(line[0], line[7], line[3]);
   gate_nand nand4(line[2], line[3], line[4]);

   gate_or or1(reset, line[4], line[7]);
   
   buf buf1(s1, line[3]);
   buf buf2(s2, line[4]);
endmodule // basculeD

module Dflip_flop(a, clk, reset, s1, s2);
   input a, clk, reset;
   output s1, s2;
   wire [3:0] line;
   wire       ignore;
   
   basculeD basc1(a, clk, reset, line[0], ignore);
   gate_not not1(clk, line[1]);
   basculeD basc2(line[0], line[1], reset, line[2], line[3]);

   buf buf1(s1, line[2]);
   buf buf1(s2, line[3]);   
endmodule // flip_flopD

memory/test/test_Dflipflop.v
module test_Dflipflop;
   reg a, clk, reset;
   wire s1, s2;

   Dflip_flop test_Dflipflop(a, clk, reset, s1, s2);

   initial
     begin
	a = 0;
	clk = 0;
	reset = 1;
	#5;
	a = 0;
	clk = 0;
	reset = 0;
	#5;
	a = 1;
	clk = 1;
	reset = 0;
	#5;
	a = 0;
	clk = 0;
	reset = 0;
	#5;
	a = 0;
	clk = 1;
	reset = 0;
	#5;
	a = 0;
	clk = 0;
	reset = 0;
	#5;
	a = 1;
	clk = 0;
	reset = 0;
	#5;
	a = 0;
	clk = 1;
	reset = 0;
	#5;
	a = 1;
	clk = 1;
	reset = 0;
	#5;
	a = 0;
	clk = 0;
	reset = 1;
	#5;
     end // initial begin
   initial
     begin
	$dumpfile("signal/signal_Dflipflop.vcd");
	$dumpvars;
     end
   initial
     begin
	$display("\t\ttime, \ta, \tclk, \ts1, \ts2");
	$monitor("%d \t%b \t%b \t%b \t%b", $time, a, clk, s1, s2);
     end
endmodule // test_Dflipflop

primitive/gate.v
module gate_not (e1, s);
   input e1;
   output s;

   assign s = ~e1;
endmodule // not

module gate_and (e1, e2, s);
   input e1;
   input e2;
   output s;

   assign s = e1 & e2;
endmodule // and

module gate_or (e1, e2, s);
   input e1, e2;
   output s;

   assign s = e1 | e2;
endmodule // or

module gate_xor (e1, e2, s);
   input e1, e2;
   output s;
 
   assign s = e1 ^ e2;
endmodule // xor

module gate_nand (e1, e2, s);
   input e1, e2;
   output s;

   assign s = e1 ~& e2;
endmodule // nand
  
module gate_nor (e1, e2, s);
   input e1, e2;
   output s;

   assign s = e1 ~| e2;
endmodule // nor

memory/signal/signal_Dflipflop.vcd
$date
	Sun May 24 00:07:01 2020
$end
$version
	Icarus Verilog
$end
$timescale
	1s
$end
$scope module gate_nor $end
$var wire 1 ! e1 $end
$var wire 1 " e2 $end
$var wire 1 # s $end
$upscope $end
$scope module test_Dflipflop $end
$var wire 1 $ s2 $end
$var wire 1 % s1 $end
$var reg 1 & a $end
$var reg 1 ' clk $end
$var reg 1 ( reset $end
$scope module test_Dflipflop $end
$var wire 1 & a $end
$var wire 1 ' clk $end
$var wire 1 ( reset $end
$var wire 1 % s1 $end
$var wire 1 $ s2 $end
$var wire 4 ) line [3:0] $end
$var wire 1 * ignore $end
$scope module basc1 $end
$var wire 1 & a $end
$var wire 1 ' clk $end
$var wire 1 ( reset $end
$var wire 1 + s1 $end
$var wire 1 * s2 $end
$var wire 8 , line [7:0] $end
$scope module and1 $end
$var wire 1 & e1 $end
$var wire 1 - e2 $end
$var wire 1 . s $end
$upscope $end
$scope module nand1 $end
$var wire 1 & e1 $end
$var wire 1 ' e2 $end
$var wire 1 / s $end
$upscope $end
$scope module nand2 $end
$var wire 1 0 e1 $end
$var wire 1 ' e2 $end
$var wire 1 1 s $end
$upscope $end
$scope module nand3 $end
$var wire 1 2 e1 $end
$var wire 1 3 e2 $end
$var wire 1 4 s $end
$upscope $end
$scope module nand4 $end
$var wire 1 5 e1 $end
$var wire 1 6 e2 $end
$var wire 1 7 s $end
$upscope $end
$scope module not1 $end
$var wire 1 8 e1 $end
$var wire 1 9 s $end
$upscope $end
$scope module or1 $end
$var wire 1 ( e1 $end
$var wire 1 : e2 $end
$var wire 1 ; s $end
$upscope $end
$scope module xor1 $end
$var wire 1 & e1 $end
$var wire 1 ( e2 $end
$var wire 1 < s $end
$upscope $end
$upscope $end
$scope module basc2 $end
$var wire 1 = a $end
$var wire 1 > clk $end
$var wire 1 ( reset $end
$var wire 1 ? s1 $end
$var wire 1 @ s2 $end
$var wire 8 A line [7:0] $end
$scope module and1 $end
$var wire 1 = e1 $end
$var wire 1 B e2 $end
$var wire 1 C s $end
$upscope $end
$scope module nand1 $end
$var wire 1 = e1 $end
$var wire 1 > e2 $end
$var wire 1 D s $end
$upscope $end
$scope module nand2 $end
$var wire 1 E e1 $end
$var wire 1 > e2 $end
$var wire 1 F s $end
$upscope $end
$scope module nand3 $end
$var wire 1 G e1 $end
$var wire 1 H e2 $end
$var wire 1 I s $end
$upscope $end
$scope module nand4 $end
$var wire 1 J e1 $end
$var wire 1 K e2 $end
$var wire 1 L s $end
$upscope $end
$scope module not1 $end
$var wire 1 M e1 $end
$var wire 1 N s $end
$upscope $end
$scope module or1 $end
$var wire 1 ( e1 $end
$var wire 1 O e2 $end
$var wire 1 P s $end
$upscope $end
$scope module xor1 $end
$var wire 1 = e1 $end
$var wire 1 ( e2 $end
$var wire 1 Q s $end
$upscope $end
$upscope $end
$scope module not1 $end
$var wire 1 ' e1 $end
$var wire 1 R s $end
$upscope $end
$upscope $end
$upscope $end
$enddefinitions $end
#0
$dumpvars
1R
1Q
1P
1O
1N
0M
1L
0K
0J
0I
1H
1G
0F
1E
1D
0C
1B
b10110011 A
1@
0?
1>
0=
1<
1;
1:
19
08
17
06
15
04
13
12
11
10
1/
0.
1-
b10110111 ,
0+
1*
b1010 )
1(
0'
0&
0%
1$
x#
z"
z!
$end
#5
0-
0B
b10010111 ,
0<
b10010011 A
0Q
0(
#10
0E
03
0N
0*
0;
1M
0:
1C
07
1B
1Q
1=
00
1+
09
1J
16
18
b11110101 A
1F
14
1.
15
0>
02
1-
11
b1001 )
0R
0/
b1101100 ,
1<
1'
1&
#15
0$
0H
1%
0@
0P
0O
1?
0L
1K
1I
0G
10
b1101100 A
0D
19
1>
08
12
0-
b111 )
1R
0.
1/
b1111 ,
0<
0'
0&
#20
1E
1N
0M
0B
0C
0Q
0=
0+
06
04
13
1*
1;
1:
1G
17
b1111 A
1D
05
0>
b10010011 ,
01
b100 )
0R
1'
#25
0%
0?
0K
1$
0I
1H
1@
1P
1O
1L
0J
b10010011 A
0F
15
1>
b10010111 ,
11
b1010 )
1R
0'
#30
00
09
18
1.
1-
b11110101 ,
1<
1&
#35
05
01
1J
10
b10010111 A
1F
19
0>
08
0-
b1000 )
0R
0.
b10010011 ,
0<
1'
0&
#40
0E
03
0N
0*
0;
1M
0:
1C
07
1B
15
b11110101 A
1Q
11
1=
00
b1001 )
1+
09
16
18
14
1.
02
1-
0/
b1101100 ,
1<
1&
#45
1$
0%
1@
0J
1O
0F
0?
1L
1*
1E
0K
0=
1:
1N
0I
0+
17
0M
1G
10
06
0C
1D
19
04
13
1B
1>
08
12
1;
b10110011 A
1Q
b1010 )
1R
0.
b10110111 ,
1/
1(
0'
0&
