alu/add.v
module add (a, b, cin, sub, s, cout);
   input a, b, cin, sub;
   output s, cout;
   wire [3:0] line;

   /*
   assign line[0] = b ^ sub;
   assign line[1] = a ^ line[0];
   assign line[2] = a & line[0];
   assign s = cin ^ line[1];
   assign line[3] =  cin & line[1];
   assign cout = line[3] | line[2];
   //*/
   gate_xor xor0 (b, sub, line[0]);
   gate_xor xor1 (a, line[0], line[1]);
   gate_xor xor2 (cin, line[1], s);
   gate_and and1 (a, line[0], line[2]);
   gate_xor and2 (cin, line[1], line[3]);
   gate_or or3 (line[3], line[2], cout);
endmodule // full_add

alu/test_full_add.v
module test;
   reg a, b, cin, sub;
   wire s, cout;

   add test_additionneur(a, b, cin, sub, s, cout);

   initial
     begin
	a = 0;
	b = 0;
	cin = 0;
	sub = 0;
	#5;
	a = 1;
	b = 0;
	cin = 0;
	sub = 0;
	#5;
	a = 0;
	b = 1;
	cin = 0;
	sub = 0;
	#5;
	a = 1;
	b = 1;
	cin = 0;
	sub = 0;
	#5;
	a = 0;
	b = 0;
	cin = 1;
	sub = 0;
	#5;
	a = 1;
	b = 0;
	cin = 1;
	sub = 0;
	#5;
	a = 0;
	b = 1;
	cin = 1;
	sub = 0;
	#5;
	a = 1;
	b = 1;
	cin = 1;
	sub = 0;
	#5;

	a = 0;
	b = 0;
	cin = 0;
	sub = 1;
	#5;
	a = 1;
	b = 0;
	cin = 0;
	sub = 1;
	#5;
	a = 0;
	b = 1;
	cin = 0;
	sub = 1;
	#5;
	a = 1;
	b = 1;
	cin = 0;
	sub = 1;
	#5;
	a = 0;
	b = 0;
	cin = 1;
	sub = 1;
	#5;
	a = 1;
	b = 0;
	cin = 1;
	sub = 1;
	#5;
	a = 0;
	b = 1;
	cin = 1;
	sub = 1;
	#5;
	a = 1;
	b = 1;
	cin = 1;
	sub = 1;
     end // initial begin
   initial
     begin
	$dumpfile("full_add.vcd");
	$dumpvars;
     end

   initial
     begin
	$display("\t\ttime,\ta,\tb, \tcin, \tsub,\ts,\tcout");
	$monitor("%d \t%b \t%b \t%b \t%b \t%b \t%b", $time, a, b, cin, sub, s, cout);
     end
endmodule // test

primitive/gate.v
module gate_not (e1, s);
   input e1;
   output s;

   assign s = ~e1;
endmodule // not

module gate_and (e1, e2, s);
   input e1;
   input e2;
   output s;

   assign s = e1 & e2;
endmodule // and

module gate_or (e1, e2, s);
   input e1, e2;
   output s;

   assign s = e1 | e2;
endmodule // or

module gate_xor (e1, e2, s);
   input e1, e2;
   output s;
 
   assign s = e1 ^ e2;
endmodule // xor

module gate_nand (e1, e2, s);
   input e1, e2;
   output s;

   assign s = e1 ~& e2;
endmodule // nand
  
module gate_nor (e1, e2, s);
   input e1, e2;
   output s;

   assign s = e1 ~| e2;
endmodule // nor

alu/full_add.vcd
$date
	Fri May 22 19:27:11 2020
$end
$version
	Icarus Verilog
$end
$timescale
	1s
$end
$scope module gate_nand $end
$var wire 1 ! e1 $end
$var wire 1 " e2 $end
$var wire 1 # s $end
$upscope $end
$scope module gate_nor $end
$var wire 1 $ e1 $end
$var wire 1 % e2 $end
$var wire 1 & s $end
$upscope $end
$scope module gate_not $end
$var wire 1 ' e1 $end
$var wire 1 ( s $end
$upscope $end
$scope module test $end
$var wire 1 ) s $end
$var wire 1 * cout $end
$var reg 1 + a $end
$var reg 1 , b $end
$var reg 1 - cin $end
$var reg 1 . sub $end
$scope module test_additionneur $end
$var wire 1 + a $end
$var wire 1 , b $end
$var wire 1 - cin $end
$var wire 1 . sub $end
$var wire 1 ) s $end
$var wire 4 / line [3:0] $end
$var wire 1 * cout $end
$scope module and1 $end
$var wire 1 + e1 $end
$var wire 1 0 e2 $end
$var wire 1 1 s $end
$upscope $end
$scope module and2 $end
$var wire 1 - e1 $end
$var wire 1 2 e2 $end
$var wire 1 3 s $end
$upscope $end
$scope module or3 $end
$var wire 1 4 e1 $end
$var wire 1 5 e2 $end
$var wire 1 * s $end
$upscope $end
$scope module xor0 $end
$var wire 1 , e1 $end
$var wire 1 . e2 $end
$var wire 1 6 s $end
$upscope $end
$scope module xor1 $end
$var wire 1 + e1 $end
$var wire 1 7 e2 $end
$var wire 1 8 s $end
$upscope $end
$scope module xor2 $end
$var wire 1 - e1 $end
$var wire 1 9 e2 $end
$var wire 1 ) s $end
$upscope $end
$upscope $end
$upscope $end
$enddefinitions $end
#0
$dumpvars
09
08
07
06
05
04
03
02
01
00
b0 /
0.
0-
0,
0+
0*
0)
z(
z'
x&
z%
z$
x#
z"
z!
$end
#5
1*
14
13
1)
12
19
b1010 /
18
1+
#10
1*
14
13
1)
10
17
12
19
16
b1011 /
18
1,
0+
#15
04
03
0)
15
02
09
11
b101 /
08
1+
#20
1*
14
00
07
05
02
09
13
1)
06
01
b1000 /
08
1-
0,
0+
#25
0*
04
03
0)
12
19
b10 /
18
1+
#30
0*
04
03
0)
10
17
12
19
16
b11 /
18
1,
0+
#35
14
1*
13
1)
15
02
09
11
b1101 /
08
1+
#40
1*
14
05
12
19
13
1)
01
b1011 /
18
1.
0-
0,
0+
#45
04
03
0)
15
02
09
11
b101 /
08
1+
#50
04
0*
03
0)
00
07
05
02
09
06
01
b0 /
08
1,
0+
#55
1*
14
13
1)
12
19
b1010 /
18
1+
#60
0*
04
10
17
12
19
03
0)
16
b11 /
18
1-
0,
0+
#65
14
1*
13
1)
15
02
09
11
b1101 /
08
1+
#70
1*
14
13
1)
00
07
05
02
09
06
01
b1000 /
08
1,
0+
#75
0*
04
03
0)
12
19
b10 /
18
1+
