alu/testbench.v
module test;
   reg a, b, cin, sub;
   wire s, cout;

   full_add test_additionneur(a, b, cin, sub, s, cout);

   initial
     begin
	a = 0;
	b = 0;
	cin = 0;
	sub = 0;
	#5;
	a = 1;
	b = 0;
	cin = 0;
	sub = 0;
	#5;
	a = 0;
	b = 1;
	cin = 0;
	sub = 0;
	#5;
	a = 1;
	b = 1;
	cin = 0;
	sub = 0;
	#5;
	a = 0;
	b = 0;
	cin = 1;
	sub = 0;
	#5;
	a = 1;
	b = 0;
	cin = 1;
	sub = 0;
	#5;
	a = 0;
	b = 1;
	cin = 1;
	sub = 0;
	#5;
	a = 1;
	b = 1;
	cin = 1;
	sub = 0;
	#5;

	a = 0;
	b = 0;
	cin = 0;
	sub = 1;
	#5;
	a = 1;
	b = 0;
	cin = 0;
	sub = 1;
	#5;
	a = 0;
	b = 1;
	cin = 0;
	sub = 1;
	#5;
	a = 1;
	b = 1;
	cin = 0;
	sub = 1;
	#5;
	a = 0;
	b = 0;
	cin = 1;
	sub = 1;
	#5;
	a = 1;
	b = 0;
	cin = 1;
	sub = 1;
	#5;
	a = 0;
	b = 1;
	cin = 1;
	sub = 1;
	#5;
	a = 1;
	b = 1;
	cin = 1;
	sub = 1;
     end // initial begin
   initial
     begin
	$dumpfile("full_add.vcd");
	$dumpvars;
     end

   initial
     begin
	$display("\t\ttime,\ta,\tb, \tsub, \tcin,\ts,\ttcout");
	$monitor("%d \t%b \t%b \t%b \t%b \t%b \t%b", $time, a, b, sub, cin, s, cout);
     end
endmodule // test

primitive/gate.v
module gate_not (e1, s);
   input e1;
   output s;

   assign s = ~e1;
endmodule // not

module gate_and (e1, e2, s);
   input e1;
   input e2;
   output s;

   assign s = e1 & e2;
endmodule // and

module gate_or (e1, e2, s);
   input e1, e2;
   output s;

   assign s = e1 | e2;
endmodule // or

module gate_xor (e1, e2, s);
   input e1, e2;
   output s;
 
   assign s = e1 ^ e2;
endmodule // xor

module gate_nand (e1, e2, s);
   input e1, e2;
   output s;

   assign s = e1 ~& e2;
endmodule // nand
  
module gate_nor (e1, e2, s);
   input e1, e2;
   output s;

   assign s = e1 ~| e2;
endmodule // nor

alu/adder.v
module full_add (a, b, cin, sub, s, cout);
   input a, b, cin, sub;
   output s, cout;
   wire [3:0] line;

   assign line[0] = b ^ sub;
   assign line[1] = a ^ line[0];
   assign line[2] = a & line[0];
   assign s = cin ^ line[1];
   assign line[3] =  cin & line[1];
   assign cout = line[3] | line[2];
   
//   gate_xor xor0 (b, sub, line[0]);
//   gate_xor xor1 (a, line[0], line[1]);
//   gate_and and1 (a, line[0], line[2]);
//   gate_xor xor2 (cin, line[1], s);
//   gate_xor and2 (cin, line[1], line[3]);
//   gate_or or3 (line[3], line[2], cout);
endmodule // full_add

module add8 (a, b, cin, sub, s, cout);
   input [7:0] a, b;
   input       cin, sub;

   output [7:0] s;
   output 	cout;

   wire [6:0] 	ret;

   full_add add0 (a[0], b[0], cin, sub, s[0], ret[0]);
   full_add add1 (a[1], b[1], ret[0], sub, s[1], ret[1]);
   full_add add2 (a[2], b[2], ret[1], sub, s[2], ret[2]);
   full_add add3 (a[3], b[3], ret[2], sub, s[3], ret[3]);
   full_add add4 (a[4], b[4], ret[3], sub, s[4], ret[4]);
   full_add add5 (a[5], b[5], ret[4], sub, s[5], ret[5]);
   full_add add6 (a[6], b[6], ret[5], sub, s[6], ret[6]);
   full_add add7 (a[7], b[7], ret[6], sub, s[7], cout);
endmodule // add8

alu/full_add.vcd
$date
	Fri May 22 17:29:15 2020
$end
$version
	Icarus Verilog
$end
$timescale
	1s
$end
$scope module add8 $end
$var wire 8 ! a [7:0] $end
$var wire 8 " b [7:0] $end
$var wire 1 # cin $end
$var wire 1 $ sub $end
$var wire 8 % s [7:0] $end
$var wire 7 & ret [6:0] $end
$var wire 1 ' cout $end
$scope module add0 $end
$var wire 1 ( a $end
$var wire 1 ) b $end
$var wire 1 # cin $end
$var wire 1 * cout $end
$var wire 1 + s $end
$var wire 1 $ sub $end
$var wire 4 , line [3:0] $end
$upscope $end
$scope module add1 $end
$var wire 1 - a $end
$var wire 1 . b $end
$var wire 1 / cin $end
$var wire 1 0 cout $end
$var wire 1 1 s $end
$var wire 1 $ sub $end
$var wire 4 2 line [3:0] $end
$upscope $end
$scope module add2 $end
$var wire 1 3 a $end
$var wire 1 4 b $end
$var wire 1 5 cin $end
$var wire 1 6 cout $end
$var wire 1 7 s $end
$var wire 1 $ sub $end
$var wire 4 8 line [3:0] $end
$upscope $end
$scope module add3 $end
$var wire 1 9 a $end
$var wire 1 : b $end
$var wire 1 ; cin $end
$var wire 1 < cout $end
$var wire 1 = s $end
$var wire 1 $ sub $end
$var wire 4 > line [3:0] $end
$upscope $end
$scope module add4 $end
$var wire 1 ? a $end
$var wire 1 @ b $end
$var wire 1 A cin $end
$var wire 1 B cout $end
$var wire 1 C s $end
$var wire 1 $ sub $end
$var wire 4 D line [3:0] $end
$upscope $end
$scope module add5 $end
$var wire 1 E a $end
$var wire 1 F b $end
$var wire 1 G cin $end
$var wire 1 H cout $end
$var wire 1 I s $end
$var wire 1 $ sub $end
$var wire 4 J line [3:0] $end
$upscope $end
$scope module add6 $end
$var wire 1 K a $end
$var wire 1 L b $end
$var wire 1 M cin $end
$var wire 1 N cout $end
$var wire 1 O s $end
$var wire 1 $ sub $end
$var wire 4 P line [3:0] $end
$upscope $end
$scope module add7 $end
$var wire 1 Q a $end
$var wire 1 R b $end
$var wire 1 S cin $end
$var wire 1 ' cout $end
$var wire 1 T s $end
$var wire 1 $ sub $end
$var wire 4 U line [3:0] $end
$upscope $end
$upscope $end
$scope module gate_and $end
$var wire 1 V e1 $end
$var wire 1 W e2 $end
$var wire 1 X s $end
$upscope $end
$scope module gate_nand $end
$var wire 1 Y e1 $end
$var wire 1 Z e2 $end
$var wire 1 [ s $end
$upscope $end
$scope module gate_nor $end
$var wire 1 \ e1 $end
$var wire 1 ] e2 $end
$var wire 1 ^ s $end
$upscope $end
$scope module gate_not $end
$var wire 1 _ e1 $end
$var wire 1 ` s $end
$upscope $end
$scope module gate_or $end
$var wire 1 a e1 $end
$var wire 1 b e2 $end
$var wire 1 c s $end
$upscope $end
$scope module gate_xor $end
$var wire 1 d e1 $end
$var wire 1 e e2 $end
$var wire 1 f s $end
$upscope $end
$scope module test $end
$var wire 1 g s $end
$var wire 1 h cout $end
$var reg 1 i a $end
$var reg 1 j b $end
$var reg 1 k cin $end
$var reg 1 l sub $end
$scope module test_additionneur $end
$var wire 1 i a $end
$var wire 1 j b $end
$var wire 1 k cin $end
$var wire 1 h cout $end
$var wire 1 g s $end
$var wire 1 l sub $end
$var wire 4 m line [3:0] $end
$upscope $end
$upscope $end
$enddefinitions $end
#0
$dumpvars
b0 m
0l
0k
0j
0i
0h
0g
xf
ze
zd
xc
zb
za
z`
z_
x^
z]
z\
x[
zZ
zY
xX
zW
zV
bx U
xT
xS
zR
zQ
bx P
xO
xN
xM
zL
zK
bx J
xI
xH
xG
zF
zE
bx D
xC
xB
xA
z@
z?
bx >
x=
x<
x;
z:
z9
bx 8
x7
x6
x5
z4
z3
bx 2
x1
x0
x/
z.
z-
bx ,
x+
x*
z)
z(
x'
bx &
bx %
z$
z#
bz "
bz !
$end
#5
1g
b10 m
1i
#10
1g
b11 m
1j
0i
#15
0g
1h
b101 m
1i
#20
0h
1g
b0 m
1k
0j
0i
#25
1h
0g
b1010 m
1i
#30
1h
0g
b1011 m
1j
0i
#35
1g
b101 m
1i
#40
0h
1g
b11 m
1l
0k
0j
0i
#45
0g
1h
b101 m
1i
#50
0g
0h
b0 m
1j
0i
#55
1g
b10 m
1i
#60
1h
0g
b1011 m
1k
0j
0i
#65
1g
b101 m
1i
#70
1g
0h
b0 m
1j
0i
#75
1h
0g
b1010 m
1i
